fetch_radio_cmat2aset/__init__.py
fetch_radio_cmat2aset/__main__.py
fetch_radio_cmat2aset/fetch_radio_cmat2aset.py
fetch_radio_cmat2aset-0.1.0a1.dist-info/entry_points.txt
fetch_radio_cmat2aset-0.1.0a1.dist-info/LICENSE
fetch_radio_cmat2aset-0.1.0a1.dist-info/WHEEL
fetch_radio_cmat2aset-0.1.0a1.dist-info/METADATA
fetch_radio_cmat2aset-0.1.0a1.dist-info/RECORD
